django_logger/__init__.py
django_logger/_version.py
django_logger/admin.py
django_logger/apps.py
django_logger/constants.py
django_logger/decorators.py
django_logger/managers.py
django_logger/middleware.py
django_logger/models.py
django_logger/services.py
django_logger/urls.py
django_logger/utils.py
django_logger/views.py
django_logger/wrapper.py
django_logger/migrations/__init__.py
unergy_logger_django-1.0.3.dist-info/licenses/LICENSE
unergy_logger_django-1.0.3.dist-info/METADATA
unergy_logger_django-1.0.3.dist-info/WHEEL
unergy_logger_django-1.0.3.dist-info/top_level.txt
unergy_logger_django-1.0.3.dist-info/RECORD
