Metadata-Version: 2.4
Name: unergy-logger-django
Version: 1.0.3
Summary: A Django app for advanced logging capabilities
Author-email: Dmoreno2903 <diegomoreno2903@gmail.com>
License: MIT License
Project-URL: Homepage, https://github.com/Dmoreno2903/django-logger
Project-URL: Repository, https://github.com/Dmoreno2903/django-logger.git
Project-URL: Issues, https://github.com/Dmoreno2903/django-logger/issues
Keywords: django,logging,audit,tracking
Classifier: Environment :: Web Environment
Classifier: Framework :: Django
Classifier: Framework :: Django :: 4.2
Classifier: Intended Audience :: Developers
Classifier: License :: OSI Approved :: MIT License
Classifier: Operating System :: OS Independent
Classifier: Programming Language :: Python
Classifier: Programming Language :: Python :: 3
Classifier: Topic :: Internet :: WWW/HTTP
Classifier: Topic :: Internet :: WWW/HTTP :: Dynamic Content
Classifier: Topic :: Software Development :: Libraries :: Python Modules
Requires-Python: >=3.10.13
License-File: LICENSE
Requires-Dist: Django>=4.2.5
Dynamic: license-file
